setup.py
rlunch/__init__.py
rlunch/command_line.py
rlunch/rlunch.py
rlunch.egg-info/PKG-INFO
rlunch.egg-info/SOURCES.txt
rlunch.egg-info/dependency_links.txt
rlunch.egg-info/entry_points.txt
rlunch.egg-info/not-zip-safe
rlunch.egg-info/requires.txt
rlunch.egg-info/top_level.txt