Metadata-Version: 1.0
Name: rlunch
Version: 0.2.3
Summary: The lunch recommendation system for Ridibooks employees
Home-page: http://github.com/minsoopark/RidiLunch
Author: Minsoo Park
Author-email: minsoo1003@gmail.com
License: MIT
Platform: UNKNOWN
